gist_control/__init__.py
gist_control/errors.py
gist_control-1.1.dist-info/LICENSE
gist_control-1.1.dist-info/METADATA
gist_control-1.1.dist-info/WHEEL
gist_control-1.1.dist-info/top_level.txt
gist_control-1.1.dist-info/RECORD
