Metadata-Version: 2.1
Name: gist-control
Version: 1.1
Summary: Interact with Github Gists!
Home-page: https://github.com/ghrlt/gist-control
Author: Gaëtan Hrlt
Author-email: gaetan.hrlt+dev@gmail.com
Project-URL: Developer website, https://ghr.lt?f=gist-control
Project-URL: Bug Tracker, https://github.com/ghrlt/gist-control/issues
Classifier: Programming Language :: Python :: 3
Classifier: License :: OSI Approved :: MIT License
Classifier: Operating System :: OS Independent
Requires-Python: >=3.6
License-File: LICENSE
Requires-Dist: requests
